fuzzygrep/__init__.py
fuzzygrep/cli.py
fuzzygrep/core/__init__.py
fuzzygrep/core/cache.py
fuzzygrep/core/indexer.py
fuzzygrep/core/loaders.py
fuzzygrep/core/searcher.py
fuzzygrep/ui/__init__.py
fuzzygrep/ui/display.py
fuzzygrep/ui/interactive.py
fuzzygrep/utils/__init__.py
fuzzygrep/utils/errors.py
fuzzygrep/utils/logging.py
fuzzygrep-1.0.0.dist-info/licenses/LICENSE
fuzzygrep-1.0.0.dist-info/METADATA
fuzzygrep-1.0.0.dist-info/WHEEL
fuzzygrep-1.0.0.dist-info/entry_points.txt
fuzzygrep-1.0.0.dist-info/top_level.txt
fuzzygrep-1.0.0.dist-info/RECORD
