Metadata-Version: 2.4
Name: fuzzygrep
Version: 1.0.0
Summary: Interactive fuzzy search for JSON and CSV files
Home-page: https://github.com/anggiAnand/fuzzygrep
Author: Anggi Ananda
Keywords: fuzzy search json csv cli interactive
Classifier: Development Status :: 4 - Beta
Classifier: Intended Audience :: Developers
Classifier: License :: OSI Approved :: MIT License
Classifier: Programming Language :: Python :: 3
Classifier: Programming Language :: Python :: 3.9
Classifier: Programming Language :: Python :: 3.10
Classifier: Programming Language :: Python :: 3.11
Classifier: Programming Language :: Python :: 3.12
Classifier: Topic :: Software Development :: Libraries :: Python Modules
Classifier: Topic :: Text Processing :: Filters
Classifier: Topic :: Utilities
Requires-Python: >=3.9
License-File: LICENSE
Requires-Dist: prompt_toolkit>=3.0.0
Requires-Dist: rapidfuzz>=3.0.0
Requires-Dist: rich>=13.0.0
Requires-Dist: typer>=0.9.0
Requires-Dist: cachetools>=5.0.0
Provides-Extra: enhanced
Requires-Dist: ijson>=3.2.0; extra == "enhanced"
Requires-Dist: pandas>=2.0.0; extra == "enhanced"
Provides-Extra: dev
Requires-Dist: pytest>=7.4.0; extra == "dev"
Requires-Dist: pytest-cov>=4.1.0; extra == "dev"
Requires-Dist: pytest-mock>=3.11.0; extra == "dev"
Requires-Dist: black>=23.0.0; extra == "dev"
Requires-Dist: flake8>=6.0.0; extra == "dev"
Requires-Dist: mypy>=1.5.0; extra == "dev"
Requires-Dist: isort>=5.12.0; extra == "dev"
Provides-Extra: all
Requires-Dist: ijson>=3.2.0; extra == "all"
Requires-Dist: pandas>=2.0.0; extra == "all"
Requires-Dist: pytest>=7.4.0; extra == "all"
Requires-Dist: pytest-cov>=4.1.0; extra == "all"
Requires-Dist: pytest-mock>=3.11.0; extra == "all"
Requires-Dist: black>=23.0.0; extra == "all"
Requires-Dist: flake8>=6.0.0; extra == "all"
Requires-Dist: mypy>=1.5.0; extra == "all"
Requires-Dist: isort>=5.12.0; extra == "all"
Dynamic: author
Dynamic: classifier
Dynamic: description
Dynamic: description-content-type
Dynamic: home-page
Dynamic: keywords
Dynamic: license-file
Dynamic: provides-extra
Dynamic: requires-dist
Dynamic: requires-python
Dynamic: summary
